tgr_wdn_query_lang/__init__.py
tgr_wdn_query_lang/generated/QueryExprLexer.interp
tgr_wdn_query_lang/generated/QueryExprLexer.py
tgr_wdn_query_lang/generated/QueryExprLexer.tokens
tgr_wdn_query_lang/generated/QueryExprParser.interp
tgr_wdn_query_lang/generated/QueryExprParser.py
tgr_wdn_query_lang/generated/QueryExprParser.tokens
tgr_wdn_query_lang/generated/QueryExprParserListener.py
tgr_wdn_query_lang/generated/QueryExprParserVisitor.py
tgr_wdn_query_lang/generated/__init__.py
tgr_wdn_query_lang/query.py
tgr_wdn_query_lang-1.1.7.dist-info/METADATA
tgr_wdn_query_lang-1.1.7.dist-info/WHEEL
tgr_wdn_query_lang-1.1.7.dist-info/RECORD
